{"numbersMidday":[{"digit":"4","index":1,"count":734},{"digit":"5","index":2,"count":732},{"digit":"6","index":2,"count":728},{"digit":"7","index":0,"count":723},{"digit":"1","index":1,"count":723},{"digit":"8","index":2,"count":722},{"digit":"3","index":2,"count":715},{"digit":"0","index":0,"count":712},{"digit":"0","index":1,"count":707},{"digit":"2","index":0,"count":704},{"digit":"2","index":2,"count":701},{"digit":"4","index":0,"count":699},{"digit":"3","index":0,"count":699},{"digit":"2","index":1,"count":698},{"digit":"1","index":2,"count":698},{"digit":"7","index":1,"count":697},{"digit":"3","index":1,"count":696},{"digit":"1","index":0,"count":695},{"digit":"9","index":0,"count":694},{"digit":"0","index":2,"count":684},{"digit":"5","index":0,"count":684},{"digit":"8","index":1,"count":684},{"digit":"8","index":0,"count":677},{"digit":"6","index":1,"count":677},{"digit":"9","index":1,"count":672},{"digit":"6","index":0,"count":664},{"digit":"5","index":1,"count":663},{"digit":"9","index":2,"count":662},{"digit":"7","index":2,"count":658},{"digit":"4","index":2,"count":651}],"numbersEvening":[{"digit":"8","index":1,"count":1524},{"digit":"3","index":0,"count":1519},{"digit":"5","index":1,"count":1515},{"digit":"7","index":1,"count":1504},{"digit":"4","index":0,"count":1500},{"digit":"4","index":2,"count":1499},{"digit":"9","index":2,"count":1495},{"digit":"8","index":2,"count":1489},{"digit":"8","index":0,"count":1484},{"digit":"1","index":1,"count":1474},{"digit":"1","index":2,"count":1472},{"digit":"9","index":1,"count":1472},{"digit":"3","index":1,"count":1470},{"digit":"0","index":1,"count":1464},{"digit":"2","index":0,"count":1461},{"digit":"0","index":0,"count":1461},{"digit":"0","index":2,"count":1461},{"digit":"2","index":2,"count":1459},{"digit":"7","index":0,"count":1459},{"digit":"5","index":0,"count":1457},{"digit":"3","index":2,"count":1457},{"digit":"9","index":0,"count":1454},{"digit":"6","index":2,"count":1442},{"digit":"4","index":1,"count":1441},{"digit":"5","index":2,"count":1437},{"digit":"6","index":0,"count":1434},{"digit":"7","index":2,"count":1433},{"digit":"6","index":1,"count":1417},{"digit":"1","index":0,"count":1415},{"digit":"2","index":1,"count":1363}],"win4Midday":[{"digit":"5","index":1,"count":744},{"digit":"1","index":0,"count":736},{"digit":"7","index":3,"count":728},{"digit":"8","index":2,"count":727},{"digit":"5","index":2,"count":725},{"digit":"0","index":0,"count":724},{"digit":"0","index":3,"count":718},{"digit":"1","index":3,"count":717},{"digit":"0","index":1,"count":716},{"digit":"2","index":1,"count":716},{"digit":"4","index":0,"count":715},{"digit":"0","index":2,"count":715},{"digit":"1","index":1,"count":711},{"digit":"8","index":3,"count":707},{"digit":"3","index":0,"count":705},{"digit":"7","index":2,"count":703},{"digit":"7","index":1,"count":701},{"digit":"5","index":0,"count":700},{"digit":"2","index":2,"count":695},{"digit":"6","index":3,"count":694},{"digit":"7","index":0,"count":694},{"digit":"6","index":2,"count":694},{"digit":"5","index":3,"count":692},{"digit":"3","index":3,"count":692},{"digit":"9","index":2,"count":686},{"digit":"2","index":0,"count":686},{"digit":"9","index":3,"count":683},{"digit":"4","index":1,"count":682},{"digit":"3","index":1,"count":680},{"digit":"9","index":0,"count":676},{"digit":"4","index":2,"count":672},{"digit":"3","index":2,"count":672},{"digit":"9","index":1,"count":670},{"digit":"8","index":1,"count":669},{"digit":"4","index":3,"count":668},{"digit":"1","index":2,"count":662},{"digit":"6","index":1,"count":662},{"digit":"8","index":0,"count":658},{"digit":"6","index":0,"count":657},{"digit":"2","index":3,"count":652}],"win4Evening":[{"digit":"2","index":0,"count":1455},{"digit":"2","index":2,"count":1444},{"digit":"2","index":1,"count":1435},{"digit":"4","index":2,"count":1429},{"digit":"0","index":2,"count":1423},{"digit":"1","index":1,"count":1421},{"digit":"6","index":3,"count":1420},{"digit":"2","index":3,"count":1415},{"digit":"7","index":3,"count":1414},{"digit":"5","index":1,"count":1411},{"digit":"9","index":3,"count":1404},{"digit":"0","index":1,"count":1400},{"digit":"7","index":2,"count":1396},{"digit":"4","index":0,"count":1394},{"digit":"8","index":3,"count":1394},{"digit":"6","index":0,"count":1393},{"digit":"5","index":3,"count":1391},{"digit":"9","index":0,"count":1389},{"digit":"9","index":2,"count":1384},{"digit":"4","index":1,"count":1384},{"digit":"9","index":1,"count":1381},{"digit":"7","index":0,"count":1381},{"digit":"3","index":0,"count":1381},{"digit":"6","index":1,"count":1378},{"digit":"8","index":0,"count":1370},{"digit":"4","index":3,"count":1370},{"digit":"8","index":2,"count":1366},{"digit":"0","index":3,"count":1366},{"digit":"0","index":0,"count":1365},{"digit":"1","index":2,"count":1363},{"digit":"5","index":2,"count":1356},{"digit":"1","index":0,"count":1356},{"digit":"8","index":1,"count":1351},{"digit":"7","index":1,"count":1341},{"digit":"5","index":0,"count":1337},{"digit":"3","index":2,"count":1336},{"digit":"1","index":3,"count":1328},{"digit":"6","index":2,"count":1324},{"digit":"3","index":3,"count":1319},{"digit":"3","index":1,"count":1319}]}